{
  "notes": [
    {
      "id": "1",
      "tittle": "Рабочая заметка",
      "description": "Напоминание про работу",
      "date": "2021-03-20",
      "text": "Придется идти на работу и работать 1"
    },
    {
      "id": "2",
      "tittle": "Рабочая заметка 2",
      "description": "Напоминание про работу 2",
      "date": "2021-03-21",
      "text": "Снова придется идти на работу и работать 2"
    },
    {
      "id": "3",
      "tittle": "Рабочая заметка 3",
      "description": "Напоминание про работу 3",
      "date": "2021-04-21",
      "text": "Снова придется идти на работу и работать 3"
    },
    {
      "id": "4",
      "tittle": "Рабочая заметка 4",
      "description": "Напоминание про работу 4",
      "date": "2021-03-21",
      "text": "Снова придется идти на работу и работать 4"
    },
    {
      "id": "5",
      "tittle": "Рабочая заметка 5",
      "description": "Напоминание про работу 5",
      "date": "2021-03-21",
      "text": "Снова придется идти на работу и работать 5"
    },
    {
      "id": "6",
      "tittle": "Рабочая заметка 6",
      "description": "Напоминание про работу 6",
      "date": "2021-03-21",
      "text": "Снова придется идти на работу и работать 6"
    },
    {
      "id": "7",
      "tittle": "Рабочая заметка 7",
      "description": "Напоминание про работу 7",
      "date": "2021-03-21",
      "text": "Снова придется идти на работу и работать 7"
    },
    {
      "id": "8",
      "tittle": "Рабочая заметка 8",
      "description": "Напоминание про работу 8",
      "date": "2021-03-21",
      "text": "Снова придется идти на работу и работать 8"
    },
    {
      "id": "9",
      "tittle": "Рабочая заметка 9",
      "description": "Напоминание про работу 9",
      "date": "2021-03-21",
      "text": "Снова придется идти на работу и работать 9"
    },
    {
      "id": "10",
      "tittle": "Рабочая заметка 10",
      "description": "Напоминание про работу 10",
      "date": "2021-03-21",
      "text": "Снова придется идти на работу и работать 10"
    },
    {
      "id": "11",
      "tittle": "Рабочая заметка 11",
      "description": "Напоминание про работу 11",
      "date": "2021-03-21",
      "text": "Снова придется идти на работу и работать 11"
    },
    {
      "id": "12",
      "tittle": "Рабочая заметка 12",
      "description": "Напоминание про работу 12",
      "date": "2021-03-21",
      "text": "Снова придется идти на работу и работать 12"
    }
  ]
}
